parathaa/__init__.py
parathaa/run_taxa_assignment.py
parathaa/run_tree_analysis.py
parathaa/utility/SILVA.species.editor.dev.R
parathaa/utility/__init__.py
parathaa/utility/assign.node.tax_flex.R
parathaa/utility/calc.error.scores.R
parathaa/utility/find.cutoffs_flex_parallel.R
parathaa/utility/nearest_neighbours_parallel.R
parathaa/utility/single.tax.R
parathaa/utility/tax.assign_parallel.R
parathaa/utility/diagnostics/__init__.py
parathaa-1.0.0.data/scripts/parathaa_plot_assignment.R
parathaa-1.0.0.dist-info/licenses/LICENSE
parathaa-1.0.0.dist-info/METADATA
parathaa-1.0.0.dist-info/WHEEL
parathaa-1.0.0.dist-info/entry_points.txt
parathaa-1.0.0.dist-info/top_level.txt
parathaa-1.0.0.dist-info/RECORD
